{"info":{"_postman_id":"b19366c4-4e16-4247-9446-2ed5bb5c0883","name":"Endpoints","schema":"https://schema.getpostman.com/json/collection/v2.0.0/collection.json"},"item":[{"name":"Users","item":[{"name":"GET","id":"6dd3cd70-a893-4737-bef6-a711a0d6a8a8","request":{"method":"GET","header":[],"url":"{{URL}}/users"},"response":[]},{"name":"GET By ID","id":"3b798512-7371-4d7b-8301-aead6dcc1d85","request":{"auth":{"type":"bearer","bearer":{"token":"{{authToken}}"}},"method":"GET","header":[],"url":"{{URL}}/users/1"},"response":[]},{"name":"POST","id":"1b9aa20f-ad94-466e-99db-6b171bacfbef","request":{"method":"POST","header":[],"body":{"mode":"raw","raw":"{\n    \"name\": \"Oscar\",\n    \"email\": \"oscar.kemuel@gmail.com\",\n    \"phone\": \"84991369577\",\n    \"password\": \"123456\",\n    \"password_confirmation\": \"123456\",\n    \"address\": {\n        \"street\": \"Rua Normal\",\n        \"city\": \"Natal\",\n        \"state\": \"RN\",\n        \"number\": 10\n    }\n}","options":{"raw":{"language":"json"}}},"url":"{{URL}}/users"},"response":[]},{"name":"PUT","id":"5422ccad-3739-47b0-ab91-f783695f2b9a","request":{"auth":{"type":"bearer","bearer":{"token":"{{authToken}}"}},"method":"PATCH","header":[],"body":{"mode":"raw","raw":"{\n    \"name\": \"Oscar\",\n    \"email\": \"oscar.kemuel5@gmail.com\",\n    \"phone\": \"84991369598\",\n    \"password\": \"123456\",\n    \"password_confirmation\": \"123456\",\n    \"address\": {\n        \"street\": \"Rua Normal\",\n        \"city\": \"Natal\",\n        \"state\": \"RN\",\n        \"number\": 10\n    }\n}","options":{"raw":{"language":"json"}}},"url":"{{URL}}/users/1"},"response":[]},{"name":"DELETE","id":"9c751448-b765-428d-9d97-887805d87a11","request":{"method":"DELETE","header":[],"url":"{{URL}}/users/1"},"response":[]},{"name":"Make Admin","id":"34bba658-b1d5-4e77-a821-dc00af05bdb2","request":{"method":"PATCH","header":[],"url":"{{URL}}/users/1/admin"},"response":[]}],"id":"d2d120cf-c94c-4fa1-8ccd-2da4ce2fc582"},{"name":"Sessions","item":[{"name":"Login","event":[{"listen":"test","script":{"type":"text/javascript","exec":["var res = pm.response.json();","","var token = res.token.token;","","pm.globals.set(\"authToken\", token);",""]}}],"id":"e3429640-64a0-4357-a119-6d36bd81c8e9","request":{"method":"POST","header":[],"body":{"mode":"raw","raw":"{\n  \"email\": \"oscar.kemuel@gmail.com\",\n  \"password\": \"123456\"  \n}","options":{"raw":{"language":"json"}}},"url":"{{URL}}/auth/login"},"response":[]},{"name":"Logout","event":[{"listen":"test","script":{"id":"435e229a-adaa-403c-ade1-3bc3492a294f","exec":[""],"type":"text/javascript"}}],"id":"9c273377-b835-4620-ba84-4f10632570b6","request":{"method":"DELETE","header":[],"url":"{{URL}}/auth/logout"},"response":[]}],"id":"0cf9b383-85a5-4036-a808-2f523257ca8c"},{"name":"Store","item":[{"name":"GET","id":"f8c380ee-2085-4ce7-b380-b62fa7d0d586","request":{"auth":{"type":"bearer","bearer":{"token":"{{authToken}}"}},"method":"GET","header":[],"url":"{{URL}}/stores"},"response":[]},{"name":"GET By ID","id":"091f3a2f-00e0-43cf-9659-a0f912d50703","request":{"auth":{"type":"bearer","bearer":{"token":"{{authToken}}"}},"method":"GET","header":[],"url":"{{URL}}/stores/1"},"response":[]},{"name":"POST","id":"e634cb94-29ec-47a6-b1ea-403a1fe913c9","request":{"auth":{"type":"bearer","bearer":{"token":"{{authToken}}"}},"method":"POST","header":[],"body":{"mode":"raw","raw":"{\n    \"name\": \"Lojinha 01\",\n    \"description\": \"Loja 001\",\n    \"address\": \"Rua Edgar Dantas, Santos Reis - 002\",\n    \"ownerId\": 1\n}","options":{"raw":{"language":"json"}}},"url":"{{URL}}/stores"},"response":[]},{"name":"PUT","id":"9b72fd08-fbf2-4a1c-801e-0c28fda745eb","request":{"auth":{"type":"bearer","bearer":{"token":"{{authToken}}"}},"method":"PUT","header":[],"body":{"mode":"raw","raw":"{\n    \"name\": \"Lojinha 01 Atualizado\",\n    \"description\": \"Loja 001\",\n    \"address\": \"Rua Edgar Dantas, Santos Reis - 002\"\n}","options":{"raw":{"language":"json"}}},"url":"{{URL}}/stores/1"},"response":[]},{"name":"DELETE","id":"0c3b11b9-1b27-473b-88ed-632a77bbaeb8","request":{"auth":{"type":"bearer","bearer":{"token":"{{authToken}}"}},"method":"DELETE","header":[],"url":"{{URL}}/stores/1"},"response":[]},{"name":"Change Owner","id":"a3f6e5fa-7e2b-4b4b-b7ab-a21c0761b3f5","request":{"auth":{"type":"bearer","bearer":{"token":"{{authToken}}"}},"method":"PATCH","header":[],"body":{"mode":"raw","raw":"{\n    \"userId\": 1\n}","options":{"raw":{"language":"json"}}},"url":"{{URL}}/stores/1/change-owner"},"response":[]},{"name":"ADD Seller","id":"13e288f5-38de-45c6-9091-0557b4a45329","request":{"auth":{"type":"bearer","bearer":{"token":"{{authToken}}"}},"method":"POST","header":[],"body":{"mode":"raw","raw":"{\n    \"userId\": 1\n}","options":{"raw":{"language":"json"}}},"url":"{{URL}}/stores/1/add-seller"},"response":[]},{"name":"DELETE Seller","id":"bfe67d1b-ebb5-41d3-a1a8-f72bfefaf389","request":{"auth":{"type":"bearer","bearer":{"token":"{{authToken}}"}},"method":"DELETE","header":[],"url":"{{URL}}/stores/1/remove-seller/1"},"response":[]},{"name":"ADD Sale","id":"c8b8e900-8695-47eb-81f5-945c3d28caa8","request":{"auth":{"type":"bearer","bearer":{"token":"{{authToken}}"}},"method":"POST","header":[],"body":{"mode":"raw","raw":"{\n    \"productId\": 1,\n    \"sellerId\": 1,\n    \"quantity\": 10\n}","options":{"raw":{"language":"json"}}},"url":"{{URL}}/stores/1/add-sale"},"response":[]}],"id":"89465beb-f9f9-433d-90f9-6068ec176022"},{"name":"Product","item":[{"name":"GET","id":"3dba2c6e-ae72-422d-a5fa-23799e8c4b8b","request":{"auth":{"type":"bearer","bearer":{"token":"{{authToken}}"}},"method":"GET","header":[],"url":"{{URL}}/products"},"response":[]},{"name":"GET By ID","id":"7c0ac0b9-e554-4a02-a9b2-ecc6819e9348","request":{"auth":{"type":"bearer","bearer":{"token":"{{authToken}}"}},"method":"GET","header":[],"url":"{{URL}}/products/1"},"response":[]},{"name":"POST","id":"0637a8be-0b64-431f-ad14-6c81d6c1daf9","request":{"auth":{"type":"bearer","bearer":{"token":"{{authToken}}"}},"method":"POST","header":[],"body":{"mode":"raw","raw":"{\n    \"name\": \"Bread\",\n    \"description\": \"Big Bread\",\n    \"price\": 200,\n    \"category\": \"food\",\n    \"quantity\": 300,\n    \"storeId\": 1\n}","options":{"raw":{"language":"json"}}},"url":"{{URL}}/products"},"response":[]},{"name":"PUT","id":"9ad23a88-7ee4-48f3-8b04-fb1b05df85b8","request":{"auth":{"type":"bearer","bearer":{"token":"{{authToken}}"}},"method":"PUT","header":[],"body":{"mode":"raw","raw":"{\n    \"name\": \"Bread\",\n    \"description\": \"Big Bread\",\n    \"price\": 200,\n    \"category\": \"food\",\n    \"quantity\": 300,\n    \"storeId\": 6\n}","options":{"raw":{"language":"json"}}},"url":"{{URL}}/products/1"},"response":[]},{"name":"DELETE","id":"cb811320-d0e7-4223-a198-10c648ddc110","request":{"auth":{"type":"bearer","bearer":{"token":"{{authToken}}"}},"method":"DELETE","header":[],"url":"{{URL}}/products/1"},"response":[]}],"id":"0b247aff-2a1a-41e2-81fb-2d5ca5af5ad5"},{"name":"CRUDS AVULSOS","item":[{"name":"Adresses","item":[{"name":"GET","id":"121f1a2e-7086-495f-9fb0-ce230f90a965","request":{"auth":{"type":"bearer","bearer":{"token":"{{authToken}}"}},"method":"GET","header":[],"url":"{{URL}}/addresses"},"response":[]},{"name":"GET By ID","id":"6a6e1807-664e-4b62-99a4-63757ecd983a","request":{"auth":{"type":"bearer","bearer":{"token":"{{authToken}}"}},"method":"GET","header":[],"url":"{{URL}}/addresses/1"},"response":[]},{"name":"POST","id":"228ab6a0-8e76-40bf-a0bd-97f3484b73f4","request":{"auth":{"type":"bearer","bearer":{"token":"{{authToken}}"}},"method":"POST","header":[],"body":{"mode":"raw","raw":"{\n    \"street\": \"RUA\",\n    \"city\": \"Parna\",\n    \"state\": \"RN\",\n    \"number\": 1\n}","options":{"raw":{"language":"json"}}},"url":"{{URL}}/addresses"},"response":[]},{"name":"PUT","id":"dd683f53-0efc-4cb4-880e-cb967991721e","request":{"auth":{"type":"bearer","bearer":{"token":"{{authToken}}"}},"method":"PUT","header":[],"body":{"mode":"raw","raw":"{\n    \"street\": \"RUA\",\n    \"city\": \"Parna\",\n    \"state\": \"RN\",\n    \"number\": 1\n}","options":{"raw":{"language":"json"}}},"url":"{{URL}}/addresses/1"},"response":[]},{"name":"DELETE","id":"54ad5585-3d8a-4587-8cfb-59d0909cec7d","request":{"auth":{"type":"bearer","bearer":{"token":"{{authToken}}"}},"method":"DELETE","header":[],"url":"{{URL}}/addresses/1"},"response":[]}],"id":"6c091c3e-87f1-412e-98af-db8515b1f8e1"},{"name":"Sellers","item":[{"name":"GET","id":"d522cb1c-20e1-4ff0-83e9-bff6cfa7cdd7","request":{"auth":{"type":"bearer","bearer":{"token":"{{authToken}}"}},"method":"GET","header":[],"url":"{{URL}}/sellers"},"response":[]},{"name":"GET By ID","id":"80ba6d9e-372a-4922-b372-500cb6041d1b","request":{"auth":{"type":"bearer","bearer":{"token":"{{authToken}}"}},"method":"GET","header":[],"url":"{{URL}}/sellers/1"},"response":[]},{"name":"POST","id":"3207b7c2-4c03-4760-b2a9-75c1975f416f","request":{"auth":{"type":"bearer","bearer":{"token":"{{authToken}}"}},"method":"POST","header":[],"body":{"mode":"raw","raw":"{\n    \"userId\": 1\n}","options":{"raw":{"language":"json"}}},"url":"{{URL}}/sellers"},"response":[]},{"name":"PUT","id":"59d40377-30ee-43ce-9841-3d421fb9281b","request":{"auth":{"type":"bearer","bearer":{"token":"{{authToken}}"}},"method":"PUT","header":[],"body":{"mode":"raw","raw":"{\n    \"userId\": 1\n}","options":{"raw":{"language":"json"}}},"url":"{{URL}}/sellers/1"},"response":[]},{"name":"DELETE","id":"b1f91a89-f7f9-4a0b-9602-1222dd841bd4","request":{"auth":{"type":"bearer","bearer":{"token":"{{authToken}}"}},"method":"DELETE","header":[],"url":"{{URL}}/sellers/1"},"response":[]}],"id":"e96e1744-7db0-4847-bfab-7a2bb9ae477a"},{"name":"Sales","item":[{"name":"GET","id":"a855466b-00e4-42df-84fb-56fbc970823b","request":{"auth":{"type":"bearer","bearer":{"token":"{{authToken}}"}},"method":"GET","header":[],"url":"{{URL}}/sales"},"response":[]},{"name":"GET By ID","id":"0e5aa382-a062-4cc8-a85e-2f5a2350984d","request":{"auth":{"type":"bearer","bearer":{"token":"{{authToken}}"}},"method":"GET","header":[],"url":"{{URL}}/sales/1"},"response":[]},{"name":"POST","id":"0baf66e7-dfb4-4681-8918-6b0f59871fe9","request":{"auth":{"type":"bearer","bearer":{"token":"{{authToken}}"}},"method":"POST","header":[],"body":{"mode":"raw","raw":"{\n    \"productId\": 1,\n    \"sellerId\": 2,\n    \"quantity\": 23,\n    \"storeId\": 1,\n    \"price\": 230\n}","options":{"raw":{"language":"json"}}},"url":"{{URL}}/sales"},"response":[]},{"name":"PUT","id":"37ca6488-f9f9-4f8b-bbc3-0a93aa238256","request":{"auth":{"type":"bearer","bearer":{"token":"{{authToken}}"}},"method":"PUT","header":[],"body":{"mode":"raw","raw":"{\n    \"productId\": 1,\n    \"sellerId\": 2,\n    \"quantity\": 23,\n    \"storeId\": 1,\n    \"price\": 230\n}","options":{"raw":{"language":"json"}}},"url":"{{URL}}/sales/1"},"response":[]},{"name":"DELETE","id":"1c29bb09-1988-4e39-91b9-580da3de0b89","request":{"auth":{"type":"bearer","bearer":{"token":"{{authToken}}"}},"method":"DELETE","header":[],"url":"{{URL}}/sales/1"},"response":[]}],"id":"9484b6e1-4acf-4aae-b88b-70d090db1626"}],"id":"7866a1de-3515-4c18-b002-02dd05fb2101"}]}